{
  "network": {
    "allowed_ips": [
      "203.0.113.10",
      "198.51.100.0/24"
    ]
  },
  "data": {
    "allowed_ledger_ids": [
      "ledger_123",
      "ledger_456"
    ],
    "allowed_org_ids": [
      "org_abc"
    ],
    "max_days": 90,
    "allow_sensitive_fields": false
  },
  "auto_execute": {
    "writes": {
      "enabled": false,
      "expires_at": null,
      "allowed_actions": []
    },
    "high_risk": {
      "enabled": false,
      "expires_at": null,
      "require_preflight": true,
      "require_idempotency": true,
      "max_export_rows": 1000,
      "allowed_actions": []
    }
  }
}
